{
  "id": "mystic-riffs",
  "name": "Mystic Riffs",
  "dateAdded": "2026-01-02T15:02:54.000Z",
  "dateUpdated": "2026-01-03T14:01:18.000Z",
  "comments": "The Spotify bio acknowledges the project as \"an AI-driven metal band specializing in experimental music created by artificial intelligence technology\".",
  "tags": [
    "audio-artifacts",
    "ai-visuals"
  ],
  "genres": [],
  "spotify": "6vESiai7KVad4r1YbNMVjR",
  "apple": "1765740083",
  "amazon": "B0DFR646BC",
  "youtube": "@MysticRiffsAI",
  "tiktok": null,
  "instagram": "mysticriffsband"
}
