{
  "id": "ravenheart",
  "name": "RavenHeart",
  "dateAdded": "2026-01-09T16:07:03.801Z",
  "dateUpdated": null,
  "disclosure": "confirmed",
  "disclosureText": null,
  "aiUsage": [],
  "indicators": [
    "ai-visuals",
    "anonymous"
  ],
  "indicatorsText": null,
  "comments": null,
  "tags": [
    "ai-visuals",
    "self-disclosed-ai",
    "anonymous",
    "no-social-presence"
  ],
  "genres": [],
  "popularity": null,
  "followers": null,
  "shScore": null,
  "spotify": "4BELZhMjQmouCeRsOSfEl2",
  "apple": "1835338302",
  "amazon": "B001HIDRLI",
  "youtube": "@RavenHeartNZ",
  "tiktok": null,
  "instagram": null
}
