{
  "id": "serenitys-soul-music-ai",
  "name": "Serenity's Soul Music AI",
  "dateAdded": "2025-12-08T10:59:12.000Z",
  "dateUpdated": "2025-12-23T16:52:06.000Z",
  "comments": null,
  "tags": [],
  "spotify": "https://open.spotify.com/artist/4ZSPmjprPFZwIn2yiL5SgG",
  "apple": "https://music.apple.com/us/artist/1822644297",
  "youtube": "https://www.youtube.com/@SerenitysSoulMusicAI-bm1fx",
  "instagram": null,
  "tiktok": "https://www.tiktok.com/@serenityssoulmusicai",
  "amazon": "https://music.amazon.com/artists/B0FFG7Q3JQ",
  "urls": []
}
